seafarer/__init__.py
seafarer/__main__.py
seafarer/__version__.py
seafarer/distance.py
seafarer-0.1.0.dist-info/LICENSE
seafarer-0.1.0.dist-info/METADATA
seafarer-0.1.0.dist-info/WHEEL
seafarer-0.1.0.dist-info/entry_points.txt
seafarer-0.1.0.dist-info/top_level.txt
seafarer-0.1.0.dist-info/RECORD
