Metadata-Version: 2.1
Name: seafarer
Version: 0.1.0
Summary: Taxicab metric on the sphere!
Home-page: https://github.com/maasglobal/seafarer
Author: Markus Schepke
Author-email: markus.schepke@maas.global
License: MIT
Project-URL: Documentation, https://github.com/maasglobal/seafarer/blob/master/README.md
Project-URL: Source, https://github.com/maasglobal/seafarer
Project-URL: Tracker, https://github.com/maasglobal/seafarer/issues
Keywords: metric,distance,sphere,taxicab,manhattan
Platform: UNKNOWN
Classifier: License :: OSI Approved :: MIT License
Classifier: Programming Language :: Python
Classifier: Programming Language :: Python :: 3
Classifier: Programming Language :: Python :: 3.6
Classifier: Programming Language :: Python :: 3.7
Classifier: Programming Language :: Python :: 3.8
Requires-Python: >=3.6.0
